filecenter/__init__.py
filecenter/data_common.py
filecenter/data_ext_to_human_readeable.py
filecenter/data_extension_desc.py
filecenter/data_type.py
filecenter-1.5.1.dist-info/LICENSE
filecenter-1.5.1.dist-info/METADATA
filecenter-1.5.1.dist-info/WHEEL
filecenter-1.5.1.dist-info/top_level.txt
filecenter-1.5.1.dist-info/RECORD
